pycasso/__init__.py
pycasso/__main__.py
pycasso/cipher.py
pycasso/constants.py
pycasso/prng.py
pycasso/shuffleseed.py
pycasso/unscramble.py
image_scramble-2.1.2.dist-info/LICENSE
image_scramble-2.1.2.dist-info/METADATA
image_scramble-2.1.2.dist-info/WHEEL
image_scramble-2.1.2.dist-info/entry_points.txt
image_scramble-2.1.2.dist-info/top_level.txt
image_scramble-2.1.2.dist-info/RECORD
