Metadata-Version: 2.1
Name: image-scramble
Version: 2.1.2
Summary: Split image into tiles and scramble/unscramble them with seed.
Home-page: https://github.com/catsital/pycasso
Author: catsital
Author-email: catshital@gmail.com
License: UNKNOWN
Project-URL: Bug Tracker, https://github.com/catsital/pycasso/issues
Platform: UNKNOWN
Classifier: Programming Language :: Python :: 3
Classifier: License :: OSI Approved :: MIT License
Classifier: Operating System :: OS Independent
License-File: LICENSE
Requires-Dist: Pillow (>=7.2.0)
Requires-Dist: Flask (==2.0.2)
Provides-Extra: all
Requires-Dist: Pillow (>=7.2.0) ; extra == 'all'
Requires-Dist: Flask (==2.0.2) ; extra == 'all'
Requires-Dist: wheel (>=0.35.1) ; extra == 'all'
Requires-Dist: flake8 (>=3.8.3) ; extra == 'all'
Requires-Dist: pytest (>=5.4.3) ; extra == 'all'
Requires-Dist: blinker (==1.4) ; extra == 'all'
Provides-Extra: setup
Requires-Dist: wheel (>=0.35.1) ; extra == 'setup'
Provides-Extra: test
Requires-Dist: flake8 (>=3.8.3) ; extra == 'test'
Requires-Dist: pytest (>=5.4.3) ; extra == 'test'
Requires-Dist: blinker (==1.4) ; extra == 'test'
